ihexer/__init__.py
ihexer/_run.py
ihexer/ihexer.py
ihexer/main.py
ihexer/py.typed
ihexer-0.3.1.dist-info/LICENSE
ihexer-0.3.1.dist-info/METADATA
ihexer-0.3.1.dist-info/WHEEL
ihexer-0.3.1.dist-info/entry_points.txt
ihexer-0.3.1.dist-info/RECORD
