Metadata-Version: 2.3
Name: ihexer
Version: 0.3.1
Summary: Parse, view and diff files in Intel HEX format.
License: MIT
Author: Avengineers
Author-email: karsten.guenther@kamg.de
Requires-Python: >=3.10,<4.0
Classifier: Development Status :: 2 - Pre-Alpha
Classifier: Intended Audience :: Developers
Classifier: License :: OSI Approved :: MIT License
Classifier: Natural Language :: English
Classifier: Operating System :: OS Independent
Classifier: Programming Language :: Python :: 3
Classifier: Programming Language :: Python :: 3.10
Classifier: Programming Language :: Python :: 3.11
Classifier: Programming Language :: Python :: 3.12
Classifier: Programming Language :: Python :: 3.13
Classifier: Topic :: Software Development :: Libraries
Requires-Dist: intelhex (>=2.3,<3.0)
Requires-Dist: py-app-dev (>=2.1,<3.0)
Requires-Dist: typer (>=0.16,<0.17)
Project-URL: Bug Tracker, https://github.com/avengineers/ihexer/issues
Project-URL: Changelog, https://github.com/avengineers/ihexer/blob/develop/CHANGELOG.md
Project-URL: Documentation, https://ihexer.readthedocs.io
Project-URL: Repository, https://github.com/avengineers/ihexer
